[{"response": "204", "statement": {"chat": 2248, "turn": 0, "author": {"label": "HS", "type": ["person"], "uri": "http://cltl.nl/leolani/world/hs"}, "utterance": "Gays should be banned from Europe and the US.", "utterance_type": "STATEMENT", "position": "0-45", "subject": {"label": "Gays", "type": [], "uri": "http://cltl.nl/leolani/world/gays"}, "predicate": {"label": "should", "type": [], "uri": "http://cltl.nl/leolani/n2mu/should"}, "object": {"label": "should banned from Europe", "type": [], "uri": "http://cltl.nl/leolani/world/should_banned_from_europe"}, "perspective": {"_certainty": "UNDERSPECIFIED", "_polarity": "UNDERSPECIFIED", "_sentiment": "UNDERSPECIFIED", "_time": null, "_emotion": "NEUTRAL"}, "context_id": null, "date": "2024-06-05T23:35:06.863354", "place": "", "place_id": null, "country": "", "region": "", "city": "", "objects": [], "people": [], "timestamp": "2024-06-05T23:35:06.935357", "triple": {"_subject": {"_id": "http://cltl.nl/leolani/world/Gays", "_label": "gays", "_offset": null, "_confidence": 0.0, "_types": ["Instance"]}, "_predicate": {"_id": "http://cltl.nl/leolani/n2mu/should", "_label": "should", "_offset": null, "_confidence": 0.0, "_cardinality": 1}, "_complement": {"_id": "http://cltl.nl/leolani/world/should_banned_from_Europe", "_label": "should-banned-from-europe", "_offset": null, "_confidence": 0.0, "_types": ["Instance"]}}, "rdf_file": "brain_log_2024-06-06-07-10-53-045317.trig"}, "thoughts": {"_statement_novelty": null, "_entity_novelty": null, "_negation_conflicts": null, "_complement_conflict": null, "_subject_gaps": null, "_complement_gaps": null, "_overlaps": null, "_trust": null}, "rdf_log_path": "../data/DIALOCONAN/ekg/train/2248/graph/2024-06-06-07-10/brain_log_2024-06-06-07-10-53-045317"}, {"response": "204", "statement": {"chat": 2248, "turn": 0, "author": {"label": "HS", "type": ["person"], "uri": "http://cltl.nl/leolani/world/hs"}, "utterance": "Gays should be banned from Europe and the US.", "utterance_type": "STATEMENT", "position": "0-45", "subject": {"label": "Gays", "type": [], "uri": "http://cltl.nl/leolani/world/gays"}, "predicate": {"label": "should", "type": [], "uri": "http://cltl.nl/leolani/n2mu/should"}, "object": {"label": "should banned", "type": [], "uri": "http://cltl.nl/leolani/world/should_banned"}, "perspective": {"_certainty": "UNDERSPECIFIED", "_polarity": "UNDERSPECIFIED", "_sentiment": "UNDERSPECIFIED", "_time": null, "_emotion": "NEUTRAL"}, "context_id": null, "date": "2024-06-05T23:35:06.863354", "place": "", "place_id": null, "country": "", "region": "", "city": "", "objects": [], "people": [], "timestamp": "2024-06-05T23:35:06.935420", "triple": {"_subject": {"_id": "http://cltl.nl/leolani/world/Gays", "_label": "gays", "_offset": null, "_confidence": 0.0, "_types": ["Instance"]}, "_predicate": {"_id": "http://cltl.nl/leolani/n2mu/should", "_label": "should", "_offset": null, "_confidence": 0.0, "_cardinality": 1}, "_complement": {"_id": "http://cltl.nl/leolani/world/should_banned", "_label": "should-banned", "_offset": null, "_confidence": 0.0, "_types": ["Instance"]}}, "rdf_file": "brain_log_2024-06-06-07-10-53-227098.trig"}, "thoughts": {"_statement_novelty": null, "_entity_novelty": null, "_negation_conflicts": null, "_complement_conflict": null, "_subject_gaps": null, "_complement_gaps": null, "_overlaps": null, "_trust": null}, "rdf_log_path": "../data/DIALOCONAN/ekg/train/2248/graph/2024-06-06-07-10/brain_log_2024-06-06-07-10-53-227098"}, {"response": "204", "statement": {"chat": 2248, "turn": 1, "author": {"label": "CN", "type": ["person"], "uri": "http://cltl.nl/leolani/world/cn"}, "utterance": "Equal rights are granted to everyone under the European Convention on Human Rights and the US Constitution. Sexual orientation doesn't change this fact.", "utterance_type": "STATEMENT", "position": "0-152", "subject": {"label": "rights", "type": [], "uri": "http://cltl.nl/leolani/world/rights"}, "predicate": {"label": "are granted to", "type": [], "uri": "http://cltl.nl/leolani/n2mu/are_granted_to"}, "object": {"label": "everyone under European Convention on Human Rights", "type": [], "uri": "http://cltl.nl/leolani/world/everyone_under_european_convention_on_human_rights"}, "perspective": {"_certainty": "UNDERSPECIFIED", "_polarity": "UNDERSPECIFIED", "_sentiment": "UNDERSPECIFIED", "_time": null, "_emotion": "NEUTRAL"}, "context_id": null, "date": "2024-06-05T23:35:06.935496", "place": "", "place_id": null, "country": "", "region": "", "city": "", "objects": [], "people": [], "timestamp": "2024-06-05T23:35:07.025435", "triple": {"_subject": {"_id": "http://cltl.nl/leolani/world/rights", "_label": "rights", "_offset": null, "_confidence": 0.0, "_types": ["Instance"]}, "_predicate": {"_id": "http://cltl.nl/leolani/n2mu/are_granted_to", "_label": "are-granted-to", "_offset": null, "_confidence": 0.0, "_cardinality": 1}, "_complement": {"_id": "http://cltl.nl/leolani/world/everyone_under_European_Convention_on_Human_Rights", "_label": "everyone-under-european-convention-on-human-rights", "_offset": null, "_confidence": 0.0, "_types": ["Instance"]}}, "rdf_file": "brain_log_2024-06-06-07-10-53-421158.trig"}, "thoughts": {"_statement_novelty": null, "_entity_novelty": null, "_negation_conflicts": null, "_complement_conflict": null, "_subject_gaps": null, "_complement_gaps": null, "_overlaps": null, "_trust": null}, "rdf_log_path": "../data/DIALOCONAN/ekg/train/2248/graph/2024-06-06-07-10/brain_log_2024-06-06-07-10-53-421158"}, {"response": "204", "statement": {"chat": 2248, "turn": 1, "author": {"label": "CN", "type": ["person"], "uri": "http://cltl.nl/leolani/world/cn"}, "utterance": "Equal rights are granted to everyone under the European Convention on Human Rights and the US Constitution. Sexual orientation doesn't change this fact.", "utterance_type": "STATEMENT", "position": "0-152", "subject": {"label": "Equal rights", "type": [], "uri": "http://cltl.nl/leolani/world/equal_rights"}, "predicate": {"label": "are granted to", "type": [], "uri": "http://cltl.nl/leolani/n2mu/are_granted_to"}, "object": {"label": "everyone", "type": [], "uri": "http://cltl.nl/leolani/world/everyone"}, "perspective": {"_certainty": "UNDERSPECIFIED", "_polarity": "UNDERSPECIFIED", "_sentiment": "UNDERSPECIFIED", "_time": null, "_emotion": "NEUTRAL"}, "context_id": null, "date": "2024-06-05T23:35:06.935496", "place": "", "place_id": null, "country": "", "region": "", "city": "", "objects": [], "people": [], "timestamp": "2024-06-05T23:35:07.025492", "triple": {"_subject": {"_id": "http://cltl.nl/leolani/world/Equal_rights", "_label": "equal-rights", "_offset": null, "_confidence": 0.0, "_types": ["Instance"]}, "_predicate": {"_id": "http://cltl.nl/leolani/n2mu/are_granted_to", "_label": "are-granted-to", "_offset": null, "_confidence": 0.0, "_cardinality": 1}, "_complement": {"_id": "http://cltl.nl/leolani/world/everyone", "_label": "everyone", "_offset": null, "_confidence": 0.0, "_types": ["Instance"]}}, "rdf_file": "brain_log_2024-06-06-07-10-53-639911.trig"}, "thoughts": {"_statement_novelty": null, "_entity_novelty": null, "_negation_conflicts": null, "_complement_conflict": null, "_subject_gaps": null, "_complement_gaps": null, "_overlaps": null, "_trust": null}, "rdf_log_path": "../data/DIALOCONAN/ekg/train/2248/graph/2024-06-06-07-10/brain_log_2024-06-06-07-10-53-639911"}, {"response": "204", "statement": {"chat": 2248, "turn": 1, "author": {"label": "CN", "type": ["person"], "uri": "http://cltl.nl/leolani/world/cn"}, "utterance": "Equal rights are granted to everyone under the European Convention on Human Rights and the US Constitution. Sexual orientation doesn't change this fact.", "utterance_type": "STATEMENT", "position": "0-152", "subject": {"label": "Equal rights", "type": [], "uri": "http://cltl.nl/leolani/world/equal_rights"}, "predicate": {"label": "are", "type": [], "uri": "http://cltl.nl/leolani/n2mu/are"}, "object": {"label": "granted", "type": [], "uri": "http://cltl.nl/leolani/world/granted"}, "perspective": {"_certainty": "UNDERSPECIFIED", "_polarity": "UNDERSPECIFIED", "_sentiment": "UNDERSPECIFIED", "_time": null, "_emotion": "NEUTRAL"}, "context_id": null, "date": "2024-06-05T23:35:06.935496", "place": "", "place_id": null, "country": "", "region": "", "city": "", "objects": [], "people": [], "timestamp": "2024-06-05T23:35:07.025516", "triple": {"_subject": {"_id": "http://cltl.nl/leolani/world/Equal_rights", "_label": "equal-rights", "_offset": null, "_confidence": 0.0, "_types": ["Instance"]}, "_predicate": {"_id": "http://cltl.nl/leolani/n2mu/are", "_label": "are", "_offset": null, "_confidence": 0.0, "_cardinality": 1}, "_complement": {"_id": "http://cltl.nl/leolani/world/granted", "_label": "granted", "_offset": null, "_confidence": 0.0, "_types": ["Instance"]}}, "rdf_file": "brain_log_2024-06-06-07-10-53-827967.trig"}, "thoughts": {"_statement_novelty": null, "_entity_novelty": null, "_negation_conflicts": null, "_complement_conflict": null, "_subject_gaps": null, "_complement_gaps": null, "_overlaps": null, "_trust": null}, "rdf_log_path": "../data/DIALOCONAN/ekg/train/2248/graph/2024-06-06-07-10/brain_log_2024-06-06-07-10-53-827967"}, {"response": "204", "statement": {"chat": 2248, "turn": 1, "author": {"label": "CN", "type": ["person"], "uri": "http://cltl.nl/leolani/world/cn"}, "utterance": "Equal rights are granted to everyone under the European Convention on Human Rights and the US Constitution. Sexual orientation doesn't change this fact.", "utterance_type": "STATEMENT", "position": "0-152", "subject": {"label": "Equal rights", "type": [], "uri": "http://cltl.nl/leolani/world/equal_rights"}, "predicate": {"label": "are granted to", "type": [], "uri": "http://cltl.nl/leolani/n2mu/are_granted_to"}, "object": {"label": "everyone under European Convention on Human Rights", "type": [], "uri": "http://cltl.nl/leolani/world/everyone_under_european_convention_on_human_rights"}, "perspective": {"_certainty": "UNDERSPECIFIED", "_polarity": "UNDERSPECIFIED", "_sentiment": "UNDERSPECIFIED", "_time": null, "_emotion": "NEUTRAL"}, "context_id": null, "date": "2024-06-05T23:35:06.935496", "place": "", "place_id": null, "country": "", "region": "", "city": "", "objects": [], "people": [], "timestamp": "2024-06-05T23:35:07.025538", "triple": {"_subject": {"_id": "http://cltl.nl/leolani/world/Equal_rights", "_label": "equal-rights", "_offset": null, "_confidence": 0.0, "_types": ["Instance"]}, "_predicate": {"_id": "http://cltl.nl/leolani/n2mu/are_granted_to", "_label": "are-granted-to", "_offset": null, "_confidence": 0.0, "_cardinality": 1}, "_complement": {"_id": "http://cltl.nl/leolani/world/everyone_under_European_Convention_on_Human_Rights", "_label": "everyone-under-european-convention-on-human-rights", "_offset": null, "_confidence": 0.0, "_types": ["Instance"]}}, "rdf_file": "brain_log_2024-06-06-07-10-54-026445.trig"}, "thoughts": {"_statement_novelty": null, "_entity_novelty": null, "_negation_conflicts": null, "_complement_conflict": null, "_subject_gaps": null, "_complement_gaps": null, "_overlaps": null, "_trust": null}, "rdf_log_path": "../data/DIALOCONAN/ekg/train/2248/graph/2024-06-06-07-10/brain_log_2024-06-06-07-10-54-026445"}, {"response": "204", "statement": {"chat": 2248, "turn": 1, "author": {"label": "CN", "type": ["person"], "uri": "http://cltl.nl/leolani/world/cn"}, "utterance": "Equal rights are granted to everyone under the European Convention on Human Rights and the US Constitution. Sexual orientation doesn't change this fact.", "utterance_type": "STATEMENT", "position": "0-152", "subject": {"label": "rights", "type": [], "uri": "http://cltl.nl/leolani/world/rights"}, "predicate": {"label": "are granted to", "type": [], "uri": "http://cltl.nl/leolani/n2mu/are_granted_to"}, "object": {"label": "everyone under Convention on Human Rights", "type": [], "uri": "http://cltl.nl/leolani/world/everyone_under_convention_on_human_rights"}, "perspective": {"_certainty": "UNDERSPECIFIED", "_polarity": "UNDERSPECIFIED", "_sentiment": "UNDERSPECIFIED", "_time": null, "_emotion": "NEUTRAL"}, "context_id": null, "date": "2024-06-05T23:35:06.935496", "place": "", "place_id": null, "country": "", "region": "", "city": "", "objects": [], "people": [], "timestamp": "2024-06-05T23:35:07.025559", "triple": {"_subject": {"_id": "http://cltl.nl/leolani/world/rights", "_label": "rights", "_offset": null, "_confidence": 0.0, "_types": ["Instance"]}, "_predicate": {"_id": "http://cltl.nl/leolani/n2mu/are_granted_to", "_label": "are-granted-to", "_offset": null, "_confidence": 0.0, "_cardinality": 1}, "_complement": {"_id": "http://cltl.nl/leolani/world/everyone_under_Convention_on_Human_Rights", "_label": "everyone-under-convention-on-human-rights", "_offset": null, "_confidence": 0.0, "_types": ["Instance"]}}, "rdf_file": "brain_log_2024-06-06-07-10-54-205627.trig"}, "thoughts": {"_statement_novelty": null, "_entity_novelty": null, "_negation_conflicts": null, "_complement_conflict": null, "_subject_gaps": null, "_complement_gaps": null, "_overlaps": null, "_trust": null}, "rdf_log_path": "../data/DIALOCONAN/ekg/train/2248/graph/2024-06-06-07-10/brain_log_2024-06-06-07-10-54-205627"}, {"response": "204", "statement": {"chat": 2248, "turn": 1, "author": {"label": "CN", "type": ["person"], "uri": "http://cltl.nl/leolani/world/cn"}, "utterance": "Equal rights are granted to everyone under the European Convention on Human Rights and the US Constitution. Sexual orientation doesn't change this fact.", "utterance_type": "STATEMENT", "position": "0-152", "subject": {"label": "rights", "type": [], "uri": "http://cltl.nl/leolani/world/rights"}, "predicate": {"label": "are granted to", "type": [], "uri": "http://cltl.nl/leolani/n2mu/are_granted_to"}, "object": {"label": "everyone", "type": [], "uri": "http://cltl.nl/leolani/world/everyone"}, "perspective": {"_certainty": "UNDERSPECIFIED", "_polarity": "UNDERSPECIFIED", "_sentiment": "UNDERSPECIFIED", "_time": null, "_emotion": "NEUTRAL"}, "context_id": null, "date": "2024-06-05T23:35:06.935496", "place": "", "place_id": null, "country": "", "region": "", "city": "", "objects": [], "people": [], "timestamp": "2024-06-05T23:35:07.025580", "triple": {"_subject": {"_id": "http://cltl.nl/leolani/world/rights", "_label": "rights", "_offset": null, "_confidence": 0.0, "_types": ["Instance"]}, "_predicate": {"_id": "http://cltl.nl/leolani/n2mu/are_granted_to", "_label": "are-granted-to", "_offset": null, "_confidence": 0.0, "_cardinality": 1}, "_complement": {"_id": "http://cltl.nl/leolani/world/everyone", "_label": "everyone", "_offset": null, "_confidence": 0.0, "_types": ["Instance"]}}, "rdf_file": "brain_log_2024-06-06-07-10-54-422376.trig"}, "thoughts": {"_statement_novelty": null, "_entity_novelty": null, "_negation_conflicts": null, "_complement_conflict": null, "_subject_gaps": null, "_complement_gaps": null, "_overlaps": null, "_trust": null}, "rdf_log_path": "../data/DIALOCONAN/ekg/train/2248/graph/2024-06-06-07-10/brain_log_2024-06-06-07-10-54-422376"}, {"response": "204", "statement": {"chat": 2248, "turn": 1, "author": {"label": "CN", "type": ["person"], "uri": "http://cltl.nl/leolani/world/cn"}, "utterance": "Equal rights are granted to everyone under the European Convention on Human Rights and the US Constitution. Sexual orientation doesn't change this fact.", "utterance_type": "STATEMENT", "position": "0-152", "subject": {"label": "rights", "type": [], "uri": "http://cltl.nl/leolani/world/rights"}, "predicate": {"label": "are granted to", "type": [], "uri": "http://cltl.nl/leolani/n2mu/are_granted_to"}, "object": {"label": "everyone under European Convention", "type": [], "uri": "http://cltl.nl/leolani/world/everyone_under_european_convention"}, "perspective": {"_certainty": "UNDERSPECIFIED", "_polarity": "UNDERSPECIFIED", "_sentiment": "UNDERSPECIFIED", "_time": null, "_emotion": "NEUTRAL"}, "context_id": null, "date": "2024-06-05T23:35:06.935496", "place": "", "place_id": null, "country": "", "region": "", "city": "", "objects": [], "people": [], "timestamp": "2024-06-05T23:35:07.025602", "triple": {"_subject": {"_id": "http://cltl.nl/leolani/world/rights", "_label": "rights", "_offset": null, "_confidence": 0.0, "_types": ["Instance"]}, "_predicate": {"_id": "http://cltl.nl/leolani/n2mu/are_granted_to", "_label": "are-granted-to", "_offset": null, "_confidence": 0.0, "_cardinality": 1}, "_complement": {"_id": "http://cltl.nl/leolani/world/everyone_under_European_Convention", "_label": "everyone-under-european-convention", "_offset": null, "_confidence": 0.0, "_types": ["Instance"]}}, "rdf_file": "brain_log_2024-06-06-07-10-54-661211.trig"}, "thoughts": {"_statement_novelty": null, "_entity_novelty": null, "_negation_conflicts": null, "_complement_conflict": null, "_subject_gaps": null, "_complement_gaps": null, "_overlaps": null, "_trust": null}, "rdf_log_path": "../data/DIALOCONAN/ekg/train/2248/graph/2024-06-06-07-10/brain_log_2024-06-06-07-10-54-661211"}, {"response": "204", "statement": {"chat": 2248, "turn": 1, "author": {"label": "CN", "type": ["person"], "uri": "http://cltl.nl/leolani/world/cn"}, "utterance": "Equal rights are granted to everyone under the European Convention on Human Rights and the US Constitution. Sexual orientation doesn't change this fact.", "utterance_type": "STATEMENT", "position": "0-152", "subject": {"label": "Equal rights", "type": [], "uri": "http://cltl.nl/leolani/world/equal_rights"}, "predicate": {"label": "are granted to", "type": [], "uri": "http://cltl.nl/leolani/n2mu/are_granted_to"}, "object": {"label": "everyone under European Convention", "type": [], "uri": "http://cltl.nl/leolani/world/everyone_under_european_convention"}, "perspective": {"_certainty": "UNDERSPECIFIED", "_polarity": "UNDERSPECIFIED", "_sentiment": "UNDERSPECIFIED", "_time": null, "_emotion": "NEUTRAL"}, "context_id": null, "date": "2024-06-05T23:35:06.935496", "place": "", "place_id": null, "country": "", "region": "", "city": "", "objects": [], "people": [], "timestamp": "2024-06-05T23:35:07.025628", "triple": {"_subject": {"_id": "http://cltl.nl/leolani/world/Equal_rights", "_label": "equal-rights", "_offset": null, "_confidence": 0.0, "_types": ["Instance"]}, "_predicate": {"_id": "http://cltl.nl/leolani/n2mu/are_granted_to", "_label": "are-granted-to", "_offset": null, "_confidence": 0.0, "_cardinality": 1}, "_complement": {"_id": "http://cltl.nl/leolani/world/everyone_under_European_Convention", "_label": "everyone-under-european-convention", "_offset": null, "_confidence": 0.0, "_types": ["Instance"]}}, "rdf_file": "brain_log_2024-06-06-07-10-54-871121.trig"}, "thoughts": {"_statement_novelty": null, "_entity_novelty": null, "_negation_conflicts": null, "_complement_conflict": null, "_subject_gaps": null, "_complement_gaps": null, "_overlaps": null, "_trust": null}, "rdf_log_path": "../data/DIALOCONAN/ekg/train/2248/graph/2024-06-06-07-10/brain_log_2024-06-06-07-10-54-871121"}, {"response": "204", "statement": {"chat": 2248, "turn": 1, "author": {"label": "CN", "type": ["person"], "uri": "http://cltl.nl/leolani/world/cn"}, "utterance": "Equal rights are granted to everyone under the European Convention on Human Rights and the US Constitution. Sexual orientation doesn't change this fact.", "utterance_type": "STATEMENT", "position": "0-152", "subject": {"label": "Equal rights", "type": [], "uri": "http://cltl.nl/leolani/world/equal_rights"}, "predicate": {"label": "are granted to", "type": [], "uri": "http://cltl.nl/leolani/n2mu/are_granted_to"}, "object": {"label": "everyone under Convention", "type": [], "uri": "http://cltl.nl/leolani/world/everyone_under_convention"}, "perspective": {"_certainty": "UNDERSPECIFIED", "_polarity": "UNDERSPECIFIED", "_sentiment": "UNDERSPECIFIED", "_time": null, "_emotion": "NEUTRAL"}, "context_id": null, "date": "2024-06-05T23:35:06.935496", "place": "", "place_id": null, "country": "", "region": "", "city": "", "objects": [], "people": [], "timestamp": "2024-06-05T23:35:07.025653", "triple": {"_subject": {"_id": "http://cltl.nl/leolani/world/Equal_rights", "_label": "equal-rights", "_offset": null, "_confidence": 0.0, "_types": ["Instance"]}, "_predicate": {"_id": "http://cltl.nl/leolani/n2mu/are_granted_to", "_label": "are-granted-to", "_offset": null, "_confidence": 0.0, "_cardinality": 1}, "_complement": {"_id": "http://cltl.nl/leolani/world/everyone_under_Convention", "_label": "everyone-under-convention", "_offset": null, "_confidence": 0.0, "_types": ["Instance"]}}, "rdf_file": "brain_log_2024-06-06-07-10-55-074272.trig"}, "thoughts": {"_statement_novelty": null, "_entity_novelty": null, "_negation_conflicts": null, "_complement_conflict": null, "_subject_gaps": null, "_complement_gaps": null, "_overlaps": null, "_trust": null}, "rdf_log_path": "../data/DIALOCONAN/ekg/train/2248/graph/2024-06-06-07-10/brain_log_2024-06-06-07-10-55-074272"}, {"response": "204", "statement": {"chat": 2248, "turn": 1, "author": {"label": "CN", "type": ["person"], "uri": "http://cltl.nl/leolani/world/cn"}, "utterance": "Equal rights are granted to everyone under the European Convention on Human Rights and the US Constitution. Sexual orientation doesn't change this fact.", "utterance_type": "STATEMENT", "position": "0-152", "subject": {"label": "rights", "type": [], "uri": "http://cltl.nl/leolani/world/rights"}, "predicate": {"label": "are granted to", "type": [], "uri": "http://cltl.nl/leolani/n2mu/are_granted_to"}, "object": {"label": "everyone under Convention", "type": [], "uri": "http://cltl.nl/leolani/world/everyone_under_convention"}, "perspective": {"_certainty": "UNDERSPECIFIED", "_polarity": "UNDERSPECIFIED", "_sentiment": "UNDERSPECIFIED", "_time": null, "_emotion": "NEUTRAL"}, "context_id": null, "date": "2024-06-05T23:35:06.935496", "place": "", "place_id": null, "country": "", "region": "", "city": "", "objects": [], "people": [], "timestamp": "2024-06-05T23:35:07.025677", "triple": {"_subject": {"_id": "http://cltl.nl/leolani/world/rights", "_label": "rights", "_offset": null, "_confidence": 0.0, "_types": ["Instance"]}, "_predicate": {"_id": "http://cltl.nl/leolani/n2mu/are_granted_to", "_label": "are-granted-to", "_offset": null, "_confidence": 0.0, "_cardinality": 1}, "_complement": {"_id": "http://cltl.nl/leolani/world/everyone_under_Convention", "_label": "everyone-under-convention", "_offset": null, "_confidence": 0.0, "_types": ["Instance"]}}, "rdf_file": "brain_log_2024-06-06-07-10-55-293303.trig"}, "thoughts": {"_statement_novelty": null, "_entity_novelty": null, "_negation_conflicts": null, "_complement_conflict": null, "_subject_gaps": null, "_complement_gaps": null, "_overlaps": null, "_trust": null}, "rdf_log_path": "../data/DIALOCONAN/ekg/train/2248/graph/2024-06-06-07-10/brain_log_2024-06-06-07-10-55-293303"}, {"response": "204", "statement": {"chat": 2248, "turn": 1, "author": {"label": "CN", "type": ["person"], "uri": "http://cltl.nl/leolani/world/cn"}, "utterance": "Equal rights are granted to everyone under the European Convention on Human Rights and the US Constitution. Sexual orientation doesn't change this fact.", "utterance_type": "STATEMENT", "position": "0-152", "subject": {"label": "rights", "type": [], "uri": "http://cltl.nl/leolani/world/rights"}, "predicate": {"label": "are", "type": [], "uri": "http://cltl.nl/leolani/n2mu/are"}, "object": {"label": "granted", "type": [], "uri": "http://cltl.nl/leolani/world/granted"}, "perspective": {"_certainty": "UNDERSPECIFIED", "_polarity": "UNDERSPECIFIED", "_sentiment": "UNDERSPECIFIED", "_time": null, "_emotion": "NEUTRAL"}, "context_id": null, "date": "2024-06-05T23:35:06.935496", "place": "", "place_id": null, "country": "", "region": "", "city": "", "objects": [], "people": [], "timestamp": "2024-06-05T23:35:07.025707", "triple": {"_subject": {"_id": "http://cltl.nl/leolani/world/rights", "_label": "rights", "_offset": null, "_confidence": 0.0, "_types": ["Instance"]}, "_predicate": {"_id": "http://cltl.nl/leolani/n2mu/are", "_label": "are", "_offset": null, "_confidence": 0.0, "_cardinality": 1}, "_complement": {"_id": "http://cltl.nl/leolani/world/granted", "_label": "granted", "_offset": null, "_confidence": 0.0, "_types": ["Instance"]}}, "rdf_file": "brain_log_2024-06-06-07-10-55-499535.trig"}, "thoughts": {"_statement_novelty": null, "_entity_novelty": null, "_negation_conflicts": null, "_complement_conflict": null, "_subject_gaps": null, "_complement_gaps": null, "_overlaps": null, "_trust": null}, "rdf_log_path": "../data/DIALOCONAN/ekg/train/2248/graph/2024-06-06-07-10/brain_log_2024-06-06-07-10-55-499535"}, {"response": "204", "statement": {"chat": 2248, "turn": 1, "author": {"label": "CN", "type": ["person"], "uri": "http://cltl.nl/leolani/world/cn"}, "utterance": "Equal rights are granted to everyone under the European Convention on Human Rights and the US Constitution. Sexual orientation doesn't change this fact.", "utterance_type": "STATEMENT", "position": "0-152", "subject": {"label": "Equal rights", "type": [], "uri": "http://cltl.nl/leolani/world/equal_rights"}, "predicate": {"label": "are granted to", "type": [], "uri": "http://cltl.nl/leolani/n2mu/are_granted_to"}, "object": {"label": "everyone under Convention on Human Rights", "type": [], "uri": "http://cltl.nl/leolani/world/everyone_under_convention_on_human_rights"}, "perspective": {"_certainty": "UNDERSPECIFIED", "_polarity": "UNDERSPECIFIED", "_sentiment": "UNDERSPECIFIED", "_time": null, "_emotion": "NEUTRAL"}, "context_id": null, "date": "2024-06-05T23:35:06.935496", "place": "", "place_id": null, "country": "", "region": "", "city": "", "objects": [], "people": [], "timestamp": "2024-06-05T23:35:07.025731", "triple": {"_subject": {"_id": "http://cltl.nl/leolani/world/Equal_rights", "_label": "equal-rights", "_offset": null, "_confidence": 0.0, "_types": ["Instance"]}, "_predicate": {"_id": "http://cltl.nl/leolani/n2mu/are_granted_to", "_label": "are-granted-to", "_offset": null, "_confidence": 0.0, "_cardinality": 1}, "_complement": {"_id": "http://cltl.nl/leolani/world/everyone_under_Convention_on_Human_Rights", "_label": "everyone-under-convention-on-human-rights", "_offset": null, "_confidence": 0.0, "_types": ["Instance"]}}, "rdf_file": "brain_log_2024-06-06-07-10-55-674283.trig"}, "thoughts": {"_statement_novelty": null, "_entity_novelty": null, "_negation_conflicts": null, "_complement_conflict": null, "_subject_gaps": null, "_complement_gaps": null, "_overlaps": null, "_trust": null}, "rdf_log_path": "../data/DIALOCONAN/ekg/train/2248/graph/2024-06-06-07-10/brain_log_2024-06-06-07-10-55-674283"}]