[{"chat": 40, "turn": 0, "author": {"label": "HS", "type": ["person"], "uri": "http://cltl.nl/leolani/world/hs"}, "utterance": "It is obvious that this girl is at risk of FGM. Her parents are Muslims!", "utterance_type": "STATEMENT", "position": "0-72", "subject": {"label": "her-parents", "type": [null], "uri": "http://cltl.nl/leolani/world/her-parents"}, "predicate": {"label": "be", "type": [], "uri": "http://cltl.nl/leolani/n2mu/be"}, "object": {"label": "muslims", "type": ["country"], "uri": "http://cltl.nl/leolani/world/muslims"}, "perspective": {"_certainty": "CERTAIN", "_polarity": "POSITIVE", "_sentiment": "NEUTRAL", "_time": null, "_emotion": "UNDERSPECIFIED"}, "context_id": null, "date": "2024-05-06T12:52:48.222114", "place": "", "place_id": null, "country": "", "region": "", "city": "", "objects": [], "people": [], "timestamp": "2024-05-06T12:52:48.915654", "triple": {"_subject": {"_id": "http://cltl.nl/leolani/world/her-parents", "_label": "her-parents", "_offset": null, "_confidence": 0.0, "_types": ["Instance"]}, "_predicate": {"_id": "http://cltl.nl/leolani/n2mu/be", "_label": "be", "_offset": null, "_confidence": 0.0, "_cardinality": 1}, "_complement": {"_id": "http://cltl.nl/leolani/world/muslims", "_label": "muslims", "_offset": null, "_confidence": 0.0, "_types": ["country", "Instance"]}}, "rdf_file": "brain_log_2024-05-06-12-53-00-865855.trig"}, {"chat": 40, "turn": 0, "author": {"label": "HS", "type": ["person"], "uri": "http://cltl.nl/leolani/world/hs"}, "utterance": "It is obvious that this girl is at risk of FGM. Her parents are Muslims!", "utterance_type": "STATEMENT", "position": "0-72", "subject": {"label": "this-girl", "type": ["person"], "uri": "http://cltl.nl/leolani/world/this-girl"}, "predicate": {"label": "locate", "type": [], "uri": "http://cltl.nl/leolani/n2mu/locate"}, "object": {"label": "risk-of-f-gm", "type": [null], "uri": "http://cltl.nl/leolani/world/risk-of-f-gm"}, "perspective": {"_certainty": "CERTAIN", "_polarity": "POSITIVE", "_sentiment": "NEUTRAL", "_time": null, "_emotion": "UNDERSPECIFIED"}, "context_id": null, "date": "2024-05-06T12:52:48.222114", "place": "", "place_id": null, "country": "", "region": "", "city": "", "objects": [], "people": [], "timestamp": "2024-05-06T12:53:02.573482", "triple": {"_subject": {"_id": "http://cltl.nl/leolani/world/this-girl", "_label": "this-girl", "_offset": null, "_confidence": 0.0, "_types": ["person", "Instance"]}, "_predicate": {"_id": "http://cltl.nl/leolani/n2mu/locate", "_label": "locate", "_offset": null, "_confidence": 0.0, "_cardinality": 1}, "_complement": {"_id": "http://cltl.nl/leolani/world/risk-of-f-gm", "_label": "risk-of-f-gm", "_offset": null, "_confidence": 0.0, "_types": ["Instance"]}}, "rdf_file": "brain_log_2024-05-06-12-53-14-335875.trig"}]