[{"response": "204", "statement": {"chat": 799, "turn": 1, "author": {"label": "CN", "type": ["person"], "uri": "http://cltl.nl/leolani/world/cn"}, "utterance": "How come I have never heard of such a thing? Islam is a religion and people can chose their own.", "utterance_type": "STATEMENT", "position": "0-96", "subject": {"label": "Islam", "type": [], "uri": "http://cltl.nl/leolani/world/islam"}, "predicate": {"label": "is", "type": [], "uri": "http://cltl.nl/leolani/n2mu/is"}, "object": {"label": "religion", "type": [], "uri": "http://cltl.nl/leolani/world/religion"}, "perspective": {"_certainty": "UNDERSPECIFIED", "_polarity": "UNDERSPECIFIED", "_sentiment": "UNDERSPECIFIED", "_time": null, "_emotion": "CURIOSITY"}, "context_id": null, "date": "2024-06-05T23:11:05.529726", "place": "", "place_id": null, "country": "", "region": "", "city": "", "objects": [], "people": [], "timestamp": "2024-06-05T23:11:05.635003", "triple": {"_subject": {"_id": "http://cltl.nl/leolani/world/Islam", "_label": "islam", "_offset": null, "_confidence": 0.0, "_types": ["Instance"]}, "_predicate": {"_id": "http://cltl.nl/leolani/n2mu/is", "_label": "is", "_offset": null, "_confidence": 0.0, "_cardinality": 1}, "_complement": {"_id": "http://cltl.nl/leolani/world/religion", "_label": "religion", "_offset": null, "_confidence": 0.0, "_types": ["Instance"]}}, "rdf_file": "brain_log_2024-06-06-06-24-11-068736.trig"}, "thoughts": {"_statement_novelty": null, "_entity_novelty": null, "_negation_conflicts": null, "_complement_conflict": null, "_subject_gaps": null, "_complement_gaps": null, "_overlaps": null, "_trust": null}, "rdf_log_path": "../data/DIALOCONAN/ekg/train/799/graph/2024-06-06-06-24/brain_log_2024-06-06-06-24-11-068736"}, {"response": "204", "statement": {"chat": 799, "turn": 1, "author": {"label": "CN", "type": ["person"], "uri": "http://cltl.nl/leolani/world/cn"}, "utterance": "How come I have never heard of such a thing? Islam is a religion and people can chose their own.", "utterance_type": "STATEMENT", "position": "0-96", "subject": {"label": "religion", "type": [], "uri": "http://cltl.nl/leolani/world/religion"}, "predicate": {"label": "can chose", "type": [], "uri": "http://cltl.nl/leolani/n2mu/can_chose"}, "object": {"label": "their own", "type": [], "uri": "http://cltl.nl/leolani/world/their_own"}, "perspective": {"_certainty": "UNDERSPECIFIED", "_polarity": "UNDERSPECIFIED", "_sentiment": "UNDERSPECIFIED", "_time": null, "_emotion": "CURIOSITY"}, "context_id": null, "date": "2024-06-05T23:11:05.529726", "place": "", "place_id": null, "country": "", "region": "", "city": "", "objects": [], "people": [], "timestamp": "2024-06-05T23:11:05.635063", "triple": {"_subject": {"_id": "http://cltl.nl/leolani/world/religion", "_label": "religion", "_offset": null, "_confidence": 0.0, "_types": ["Instance"]}, "_predicate": {"_id": "http://cltl.nl/leolani/n2mu/can_chose", "_label": "can-chose", "_offset": null, "_confidence": 0.0, "_cardinality": 1}, "_complement": {"_id": "http://cltl.nl/leolani/world/their_own", "_label": "their-own", "_offset": null, "_confidence": 0.0, "_types": ["Instance"]}}, "rdf_file": "brain_log_2024-06-06-06-24-11-290301.trig"}, "thoughts": {"_statement_novelty": null, "_entity_novelty": null, "_negation_conflicts": null, "_complement_conflict": null, "_subject_gaps": null, "_complement_gaps": null, "_overlaps": null, "_trust": null}, "rdf_log_path": "../data/DIALOCONAN/ekg/train/799/graph/2024-06-06-06-24/brain_log_2024-06-06-06-24-11-290301"}, {"response": "204", "statement": {"chat": 799, "turn": 1, "author": {"label": "CN", "type": ["person"], "uri": "http://cltl.nl/leolani/world/cn"}, "utterance": "How come I have never heard of such a thing? Islam is a religion and people can chose their own.", "utterance_type": "STATEMENT", "position": "0-96", "subject": {"label": "people", "type": [], "uri": "http://cltl.nl/leolani/world/people"}, "predicate": {"label": "can chose", "type": [], "uri": "http://cltl.nl/leolani/n2mu/can_chose"}, "object": {"label": "their own", "type": [], "uri": "http://cltl.nl/leolani/world/their_own"}, "perspective": {"_certainty": "UNDERSPECIFIED", "_polarity": "UNDERSPECIFIED", "_sentiment": "UNDERSPECIFIED", "_time": null, "_emotion": "CURIOSITY"}, "context_id": null, "date": "2024-06-05T23:11:05.529726", "place": "", "place_id": null, "country": "", "region": "", "city": "", "objects": [], "people": [], "timestamp": "2024-06-05T23:11:05.636181", "triple": {"_subject": {"_id": "http://cltl.nl/leolani/world/people", "_label": "people", "_offset": null, "_confidence": 0.0, "_types": ["Instance"]}, "_predicate": {"_id": "http://cltl.nl/leolani/n2mu/can_chose", "_label": "can-chose", "_offset": null, "_confidence": 0.0, "_cardinality": 1}, "_complement": {"_id": "http://cltl.nl/leolani/world/their_own", "_label": "their-own", "_offset": null, "_confidence": 0.0, "_types": ["Instance"]}}, "rdf_file": "brain_log_2024-06-06-06-24-12-126958.trig"}, "thoughts": {"_statement_novelty": null, "_entity_novelty": null, "_negation_conflicts": null, "_complement_conflict": null, "_subject_gaps": null, "_complement_gaps": null, "_overlaps": null, "_trust": null}, "rdf_log_path": "../data/DIALOCONAN/ekg/train/799/graph/2024-06-06-06-24/brain_log_2024-06-06-06-24-12-126958"}]