[{"chat": 568, "turn": 0, "author": {"label": "HS", "type": ["person"]}, "utterance": "Women desperately looking for men are just unacceptable.", "utterance_type": "STATEMENT", "position": "0-56", "subject": {"label": "Women", "type": []}, "predicate": {"label": "are", "type": []}, "object": {"label": "just unacceptable", "type": []}, "perspective": {"emotion": "EmotionType.GO:NEUTRAL"}, "context_id": null, "date": "2024-06-05T23:07:39.763386", "place": "", "place_id": null, "country": "", "region": "", "city": "", "objects": [], "people": [], "timestamp": "2024-06-05T23:07:39.838348"}, {"chat": 568, "turn": 0, "author": {"label": "HS", "type": ["person"]}, "utterance": "Women desperately looking for men are just unacceptable.", "utterance_type": "STATEMENT", "position": "0-56", "subject": {"label": "Women", "type": []}, "predicate": {"label": "are", "type": []}, "object": {"label": "unacceptable", "type": []}, "perspective": {"emotion": "EmotionType.GO:NEUTRAL"}, "context_id": null, "date": "2024-06-05T23:07:39.763386", "place": "", "place_id": null, "country": "", "region": "", "city": "", "objects": [], "people": [], "timestamp": "2024-06-05T23:07:39.838419"}, {"chat": 568, "turn": 1, "author": {"label": "CN", "type": ["person"]}, "utterance": "If women truly wanted to have relationships and fulfilment they should be allowed to, not being pressured into giving up on what they want.", "utterance_type": "STATEMENT", "position": "0-139", "subject": {"label": "women", "type": []}, "predicate": {"label": "truly wanted", "type": []}, "object": {"label": "to have", "type": []}, "perspective": {"emotion": "EmotionType.GO:NEUTRAL"}, "context_id": null, "date": "2024-06-05T23:07:39.838500", "place": "", "place_id": null, "country": "", "region": "", "city": "", "objects": [], "people": [], "timestamp": "2024-06-05T23:07:39.964458"}, {"chat": 568, "turn": 1, "author": {"label": "CN", "type": ["person"]}, "utterance": "If women truly wanted to have relationships and fulfilment they should be allowed to, not being pressured into giving up on what they want.", "utterance_type": "STATEMENT", "position": "0-139", "subject": {"label": "women", "type": []}, "predicate": {"label": "wanted", "type": []}, "object": {"label": "have", "type": []}, "perspective": {"emotion": "EmotionType.GO:NEUTRAL"}, "context_id": null, "date": "2024-06-05T23:07:39.838500", "place": "", "place_id": null, "country": "", "region": "", "city": "", "objects": [], "people": [], "timestamp": "2024-06-05T23:07:39.964517"}, {"chat": 568, "turn": 1, "author": {"label": "CN", "type": ["person"]}, "utterance": "If women truly wanted to have relationships and fulfilment they should be allowed to, not being pressured into giving up on what they want.", "utterance_type": "STATEMENT", "position": "0-139", "subject": {"label": "women", "type": []}, "predicate": {"label": "wanted", "type": []}, "object": {"label": "to have", "type": []}, "perspective": {"emotion": "EmotionType.GO:NEUTRAL"}, "context_id": null, "date": "2024-06-05T23:07:39.838500", "place": "", "place_id": null, "country": "", "region": "", "city": "", "objects": [], "people": [], "timestamp": "2024-06-05T23:07:39.964540"}, {"chat": 568, "turn": 1, "author": {"label": "CN", "type": ["person"]}, "utterance": "If women truly wanted to have relationships and fulfilment they should be allowed to, not being pressured into giving up on what they want.", "utterance_type": "STATEMENT", "position": "0-139", "subject": {"label": "women", "type": []}, "predicate": {"label": "have", "type": []}, "object": {"label": "relationships", "type": []}, "perspective": {"emotion": "EmotionType.GO:NEUTRAL"}, "context_id": null, "date": "2024-06-05T23:07:39.838500", "place": "", "place_id": null, "country": "", "region": "", "city": "", "objects": [], "people": [], "timestamp": "2024-06-05T23:07:39.964562"}, {"chat": 568, "turn": 1, "author": {"label": "CN", "type": ["person"]}, "utterance": "If women truly wanted to have relationships and fulfilment they should be allowed to, not being pressured into giving up on what they want.", "utterance_type": "STATEMENT", "position": "0-139", "subject": {"label": "women", "type": []}, "predicate": {"label": "truly wanted", "type": []}, "object": {"label": "have", "type": []}, "perspective": {"emotion": "EmotionType.GO:NEUTRAL"}, "context_id": null, "date": "2024-06-05T23:07:39.838500", "place": "", "place_id": null, "country": "", "region": "", "city": "", "objects": [], "people": [], "timestamp": "2024-06-05T23:07:39.964590"}, {"chat": 568, "turn": 2, "author": {"label": "HS", "type": ["person"]}, "utterance": "Women already do what they want, and because of this they obviously are becoming the butt of \"sexist\" jokes. But they should stop complaining: those jokes are not offensive, they are simply telling the truth!", "utterance_type": "STATEMENT", "position": "0-208", "subject": {"label": "they", "type": []}, "predicate": {"label": "are becoming", "type": []}, "object": {"label": "butt of jokes", "type": []}, "perspective": {"emotion": "EmotionType.GO:NEUTRAL"}, "context_id": null, "date": "2024-06-05T23:07:39.964666", "place": "", "place_id": null, "country": "", "region": "", "city": "", "objects": [], "people": [], "timestamp": "2024-06-05T23:07:40.076997"}, {"chat": 568, "turn": 2, "author": {"label": "HS", "type": ["person"]}, "utterance": "Women already do what they want, and because of this they obviously are becoming the butt of \"sexist\" jokes. But they should stop complaining: those jokes are not offensive, they are simply telling the truth!", "utterance_type": "STATEMENT", "position": "0-208", "subject": {"label": "they", "type": []}, "predicate": {"label": "obviously are becoming", "type": []}, "object": {"label": "butt of sexist jokes", "type": []}, "perspective": {"emotion": "EmotionType.GO:NEUTRAL"}, "context_id": null, "date": "2024-06-05T23:07:39.964666", "place": "", "place_id": null, "country": "", "region": "", "city": "", "objects": [], "people": [], "timestamp": "2024-06-05T23:07:40.077051"}, {"chat": 568, "turn": 2, "author": {"label": "HS", "type": ["person"]}, "utterance": "Women already do what they want, and because of this they obviously are becoming the butt of \"sexist\" jokes. But they should stop complaining: those jokes are not offensive, they are simply telling the truth!", "utterance_type": "STATEMENT", "position": "0-208", "subject": {"label": "they", "type": []}, "predicate": {"label": "obviously are becoming", "type": []}, "object": {"label": "butt of jokes", "type": []}, "perspective": {"emotion": "EmotionType.GO:NEUTRAL"}, "context_id": null, "date": "2024-06-05T23:07:39.964666", "place": "", "place_id": null, "country": "", "region": "", "city": "", "objects": [], "people": [], "timestamp": "2024-06-05T23:07:40.077081"}, {"chat": 568, "turn": 2, "author": {"label": "HS", "type": ["person"]}, "utterance": "Women already do what they want, and because of this they obviously are becoming the butt of \"sexist\" jokes. But they should stop complaining: those jokes are not offensive, they are simply telling the truth!", "utterance_type": "STATEMENT", "position": "0-208", "subject": {"label": "they", "type": []}, "predicate": {"label": "are becoming", "type": []}, "object": {"label": "butt of sexist jokes", "type": []}, "perspective": {"emotion": "EmotionType.GO:NEUTRAL"}, "context_id": null, "date": "2024-06-05T23:07:39.964666", "place": "", "place_id": null, "country": "", "region": "", "city": "", "objects": [], "people": [], "timestamp": "2024-06-05T23:07:40.077103"}, {"chat": 568, "turn": 2, "author": {"label": "HS", "type": ["person"]}, "utterance": "Women already do what they want, and because of this they obviously are becoming the butt of \"sexist\" jokes. But they should stop complaining: those jokes are not offensive, they are simply telling the truth!", "utterance_type": "STATEMENT", "position": "0-208", "subject": {"label": "they", "type": []}, "predicate": {"label": "butt of", "type": []}, "object": {"label": "jokes", "type": []}, "perspective": {"emotion": "EmotionType.GO:NEUTRAL"}, "context_id": null, "date": "2024-06-05T23:07:39.964666", "place": "", "place_id": null, "country": "", "region": "", "city": "", "objects": [], "people": [], "timestamp": "2024-06-05T23:07:40.077125"}, {"chat": 568, "turn": 2, "author": {"label": "HS", "type": ["person"]}, "utterance": "Women already do what they want, and because of this they obviously are becoming the butt of \"sexist\" jokes. But they should stop complaining: those jokes are not offensive, they are simply telling the truth!", "utterance_type": "STATEMENT", "position": "0-208", "subject": {"label": "they", "type": []}, "predicate": {"label": "obviously are becoming", "type": []}, "object": {"label": "butt", "type": []}, "perspective": {"emotion": "EmotionType.GO:NEUTRAL"}, "context_id": null, "date": "2024-06-05T23:07:39.964666", "place": "", "place_id": null, "country": "", "region": "", "city": "", "objects": [], "people": [], "timestamp": "2024-06-05T23:07:40.077146"}, {"chat": 568, "turn": 2, "author": {"label": "HS", "type": ["person"]}, "utterance": "Women already do what they want, and because of this they obviously are becoming the butt of \"sexist\" jokes. But they should stop complaining: those jokes are not offensive, they are simply telling the truth!", "utterance_type": "STATEMENT", "position": "0-208", "subject": {"label": "they", "type": []}, "predicate": {"label": "obviously are becoming because", "type": []}, "object": {"label": "this", "type": []}, "perspective": {"emotion": "EmotionType.GO:NEUTRAL"}, "context_id": null, "date": "2024-06-05T23:07:39.964666", "place": "", "place_id": null, "country": "", "region": "", "city": "", "objects": [], "people": [], "timestamp": "2024-06-05T23:07:40.077167"}, {"chat": 568, "turn": 2, "author": {"label": "HS", "type": ["person"]}, "utterance": "Women already do what they want, and because of this they obviously are becoming the butt of \"sexist\" jokes. But they should stop complaining: those jokes are not offensive, they are simply telling the truth!", "utterance_type": "STATEMENT", "position": "0-208", "subject": {"label": "they", "type": []}, "predicate": {"label": "butt of", "type": []}, "object": {"label": "sexist jokes", "type": []}, "perspective": {"emotion": "EmotionType.GO:NEUTRAL"}, "context_id": null, "date": "2024-06-05T23:07:39.964666", "place": "", "place_id": null, "country": "", "region": "", "city": "", "objects": [], "people": [], "timestamp": "2024-06-05T23:07:40.077189"}, {"chat": 568, "turn": 2, "author": {"label": "HS", "type": ["person"]}, "utterance": "Women already do what they want, and because of this they obviously are becoming the butt of \"sexist\" jokes. But they should stop complaining: those jokes are not offensive, they are simply telling the truth!", "utterance_type": "STATEMENT", "position": "0-208", "subject": {"label": "they", "type": []}, "predicate": {"label": "are becoming", "type": []}, "object": {"label": "butt", "type": []}, "perspective": {"emotion": "EmotionType.GO:NEUTRAL"}, "context_id": null, "date": "2024-06-05T23:07:39.964666", "place": "", "place_id": null, "country": "", "region": "", "city": "", "objects": [], "people": [], "timestamp": "2024-06-05T23:07:40.077210"}, {"chat": 568, "turn": 2, "author": {"label": "HS", "type": ["person"]}, "utterance": "Women already do what they want, and because of this they obviously are becoming the butt of \"sexist\" jokes. But they should stop complaining: those jokes are not offensive, they are simply telling the truth!", "utterance_type": "STATEMENT", "position": "0-208", "subject": {"label": "they", "type": []}, "predicate": {"label": "are becoming because", "type": []}, "object": {"label": "this", "type": []}, "perspective": {"emotion": "EmotionType.GO:NEUTRAL"}, "context_id": null, "date": "2024-06-05T23:07:39.964666", "place": "", "place_id": null, "country": "", "region": "", "city": "", "objects": [], "people": [], "timestamp": "2024-06-05T23:07:40.077234"}, {"chat": 568, "turn": 2, "author": {"label": "HS", "type": ["person"]}, "utterance": "Women already do what they want, and because of this they obviously are becoming the butt of \"sexist\" jokes. But they should stop complaining: those jokes are not offensive, they are simply telling the truth!", "utterance_type": "STATEMENT", "position": "0-208", "subject": {"label": "they", "type": []}, "predicate": {"label": "are simply telling", "type": []}, "object": {"label": "truth", "type": []}, "perspective": {"emotion": "EmotionType.GO:NEUTRAL"}, "context_id": null, "date": "2024-06-05T23:07:39.964666", "place": "", "place_id": null, "country": "", "region": "", "city": "", "objects": [], "people": [], "timestamp": "2024-06-05T23:07:40.077255"}, {"chat": 568, "turn": 2, "author": {"label": "HS", "type": ["person"]}, "utterance": "Women already do what they want, and because of this they obviously are becoming the butt of \"sexist\" jokes. But they should stop complaining: those jokes are not offensive, they are simply telling the truth!", "utterance_type": "STATEMENT", "position": "0-208", "subject": {"label": "they", "type": []}, "predicate": {"label": "are telling", "type": []}, "object": {"label": "truth", "type": []}, "perspective": {"emotion": "EmotionType.GO:NEUTRAL"}, "context_id": null, "date": "2024-06-05T23:07:39.964666", "place": "", "place_id": null, "country": "", "region": "", "city": "", "objects": [], "people": [], "timestamp": "2024-06-05T23:07:40.077276"}, {"chat": 568, "turn": 3, "author": {"label": "CN", "type": ["person"]}, "utterance": "You can blame women or whatever, but don't you think it is more useful to blame the person stereotyping others?", "utterance_type": "STATEMENT", "position": "0-111", "subject": {"label": "You", "type": []}, "predicate": {"label": "can blame", "type": []}, "object": {"label": "women", "type": []}, "perspective": {"emotion": "EmotionType.GO:NEUTRAL"}, "context_id": null, "date": "2024-06-05T23:07:40.077348", "place": "", "place_id": null, "country": "", "region": "", "city": "", "objects": [], "people": [], "timestamp": "2024-06-05T23:07:40.164907"}]