[{"chat": 1420, "turn": 0, "author": {"label": "HS", "type": ["person"]}, "utterance": "Faggots are violent: we need to get rid of them.", "utterance_type": "STATEMENT", "position": "0-48", "subject": {"label": "Faggots", "type": []}, "predicate": {"label": "are", "type": []}, "object": {"label": "violent", "type": []}, "perspective": {"emotion": "EmotionType.GO:NEUTRAL"}, "context_id": null, "date": "2024-06-05T23:11:15.292210", "place": "", "place_id": null, "country": "", "region": "", "city": "", "objects": [], "people": [], "timestamp": "2024-06-05T23:11:15.391985"}, {"chat": 1420, "turn": 0, "author": {"label": "HS", "type": ["person"]}, "utterance": "Faggots are violent: we need to get rid of them.", "utterance_type": "STATEMENT", "position": "0-48", "subject": {"label": "we", "type": []}, "predicate": {"label": "get", "type": []}, "object": {"label": "rid of them", "type": []}, "perspective": {"emotion": "EmotionType.GO:NEUTRAL"}, "context_id": null, "date": "2024-06-05T23:11:15.292210", "place": "", "place_id": null, "country": "", "region": "", "city": "", "objects": [], "people": [], "timestamp": "2024-06-05T23:11:15.392044"}, {"chat": 1420, "turn": 0, "author": {"label": "HS", "type": ["person"]}, "utterance": "Faggots are violent: we need to get rid of them.", "utterance_type": "STATEMENT", "position": "0-48", "subject": {"label": "we", "type": []}, "predicate": {"label": "need", "type": []}, "object": {"label": "get", "type": []}, "perspective": {"emotion": "EmotionType.GO:NEUTRAL"}, "context_id": null, "date": "2024-06-05T23:11:15.292210", "place": "", "place_id": null, "country": "", "region": "", "city": "", "objects": [], "people": [], "timestamp": "2024-06-05T23:11:15.392078"}, {"chat": 1420, "turn": 0, "author": {"label": "HS", "type": ["person"]}, "utterance": "Faggots are violent: we need to get rid of them.", "utterance_type": "STATEMENT", "position": "0-48", "subject": {"label": "we", "type": []}, "predicate": {"label": "need", "type": []}, "object": {"label": "to get", "type": []}, "perspective": {"emotion": "EmotionType.GO:NEUTRAL"}, "context_id": null, "date": "2024-06-05T23:11:15.292210", "place": "", "place_id": null, "country": "", "region": "", "city": "", "objects": [], "people": [], "timestamp": "2024-06-05T23:11:15.392101"}, {"chat": 1420, "turn": 0, "author": {"label": "HS", "type": ["person"]}, "utterance": "Faggots are violent: we need to get rid of them.", "utterance_type": "STATEMENT", "position": "0-48", "subject": {"label": "we", "type": []}, "predicate": {"label": "get", "type": []}, "object": {"label": "rid", "type": []}, "perspective": {"emotion": "EmotionType.GO:NEUTRAL"}, "context_id": null, "date": "2024-06-05T23:11:15.292210", "place": "", "place_id": null, "country": "", "region": "", "city": "", "objects": [], "people": [], "timestamp": "2024-06-05T23:11:15.392122"}, {"chat": 1420, "turn": 1, "author": {"label": "CN", "type": ["person"]}, "utterance": "Gay men have been shown time and time again to be very peaceful people.", "utterance_type": "STATEMENT", "position": "0-71", "subject": {"label": "Gay men", "type": []}, "predicate": {"label": "have", "type": []}, "object": {"label": "have shown again", "type": []}, "perspective": {"emotion": "EmotionType.GO:APPROVAL"}, "context_id": null, "date": "2024-06-05T23:11:15.392194", "place": "", "place_id": null, "country": "", "region": "", "city": "", "objects": [], "people": [], "timestamp": "2024-06-05T23:11:15.490159"}, {"chat": 1420, "turn": 1, "author": {"label": "CN", "type": ["person"]}, "utterance": "Gay men have been shown time and time again to be very peaceful people.", "utterance_type": "STATEMENT", "position": "0-71", "subject": {"label": "Gay men", "type": []}, "predicate": {"label": "be", "type": []}, "object": {"label": "people", "type": []}, "perspective": {"emotion": "EmotionType.GO:APPROVAL"}, "context_id": null, "date": "2024-06-05T23:11:15.392194", "place": "", "place_id": null, "country": "", "region": "", "city": "", "objects": [], "people": [], "timestamp": "2024-06-05T23:11:15.490217"}, {"chat": 1420, "turn": 1, "author": {"label": "CN", "type": ["person"]}, "utterance": "Gay men have been shown time and time again to be very peaceful people.", "utterance_type": "STATEMENT", "position": "0-71", "subject": {"label": "Gay men", "type": []}, "predicate": {"label": "be", "type": []}, "object": {"label": "very peaceful people", "type": []}, "perspective": {"emotion": "EmotionType.GO:APPROVAL"}, "context_id": null, "date": "2024-06-05T23:11:15.392194", "place": "", "place_id": null, "country": "", "region": "", "city": "", "objects": [], "people": [], "timestamp": "2024-06-05T23:11:15.490242"}, {"chat": 1420, "turn": 1, "author": {"label": "CN", "type": ["person"]}, "utterance": "Gay men have been shown time and time again to be very peaceful people.", "utterance_type": "STATEMENT", "position": "0-71", "subject": {"label": "Gay men", "type": []}, "predicate": {"label": "be", "type": []}, "object": {"label": "peaceful people", "type": []}, "perspective": {"emotion": "EmotionType.GO:APPROVAL"}, "context_id": null, "date": "2024-06-05T23:11:15.392194", "place": "", "place_id": null, "country": "", "region": "", "city": "", "objects": [], "people": [], "timestamp": "2024-06-05T23:11:15.490265"}, {"chat": 1420, "turn": 1, "author": {"label": "CN", "type": ["person"]}, "utterance": "Gay men have been shown time and time again to be very peaceful people.", "utterance_type": "STATEMENT", "position": "0-71", "subject": {"label": "Gay men", "type": []}, "predicate": {"label": "have", "type": []}, "object": {"label": "have shown", "type": []}, "perspective": {"emotion": "EmotionType.GO:APPROVAL"}, "context_id": null, "date": "2024-06-05T23:11:15.392194", "place": "", "place_id": null, "country": "", "region": "", "city": "", "objects": [], "people": [], "timestamp": "2024-06-05T23:11:15.490289"}]